aarish_api/__init__.py
aarish_api/api_function.py
aarish_api-0.0.4.dist-info/LICENSE
aarish_api-0.0.4.dist-info/METADATA
aarish_api-0.0.4.dist-info/WHEEL
aarish_api-0.0.4.dist-info/top_level.txt
aarish_api-0.0.4.dist-info/RECORD
