Metadata-Version: 2.1
Name: aarish-api
Version: 0.0.4
Summary: Library with function for face recognition
Author: Aarish Technologies Inc.
Author-email: <sayantan@aarishtech.com>
Keywords: python,Computer Vision,Recognition,FaceNet
Classifier: Development Status :: 1 - Planning
Classifier: Intended Audience :: Developers
Classifier: Programming Language :: Python :: 3
Classifier: Operating System :: Unix
Classifier: Operating System :: MacOS :: MacOS X
Classifier: Operating System :: Microsoft :: Windows
License-File: LICENSE
Requires-Dist: requests
